[
  { "@": "100", "score": 75 },
  { "@yArOsUlAv": "—", "score": 62 },
  { "@": "—", "score": 34 },
  { "name": "—", "score": 0 },
  { "name": "—", "score": 0 },
  { "name": "—", "score": 0 },
  { "name": "—", "score": 0 },
  { "name": "—", "score": 0 },
  { "name": "—", "score": 0 },
  { "name": "—", "score": 0 },
  { "name": "—", "score": 0 },
  { "name": "—", "score": 0 },
  { "name": "—", "score": 0 },
  { "name": "—", "score": 0 },
  { "name": "—", "score": 0 },
  { "name": "—", "score": 0 },
  { "name": "—", "score": 0 },
  { "name": "—", "score": 0 },
  { "name": "—", "score": 0 },
  { "name": "—", "score": 0 },
  { "name": "—", "score": 0 },
  { "name": "—", "score": 0 },
  { "name": "—", "score": 0 },
  { "name": "—", "score": 0 },
  { "name": "—", "score": 0 },
  { "name": "—", "score": 0 },
  { "name": "—", "score": 0 },
  { "name": "—", "score": 0 },
  { "name": "—", "score": 0 },
  { "name": "—", "score": 0 },
  { "name": "—", "score": 0 },
  { "name": "—", "score": 0 },
  { "name": "—", "score": 0 },
  { "name": "—", "score": 0 },
  { "name": "—", "score": 0 },
  { "name": "—", "score": 0 },
  { "name": "—", "score": 0 },
  { "name": "—", "score": 0 },
  { "name": "—", "score": 0 },
  { "name": "—", "score": 0 },
  { "name": "—", "score": 0 },
  { "name": "—", "score": 0 },
  { "name": "—", "score": 0 },
  { "name": "—", "score": 0 },
  { "name": "—", "score": 0 },
  { "name": "—", "score": 0 },
  { "name": "—", "score": 0 },
  { "name": "—", "score": 0 },
  { "name": "—", "score": 0 },
  { "name": "—", "score": 0 }
]
